{"symbols":{"AppComponent":{"hasNamespace":false,"type":0,"moduleName":"app.component","relativePath":"src\\app\\app.component"},"AppModule":{"hasNamespace":false,"type":0,"moduleName":"app.module","relativePath":"src\\app\\app.module"},"UbicacionesPageModule":{"hasNamespace":false,"type":0,"moduleName":"ubicaciones.module","relativePath":"src\\app\\ubicaciones\\ubicaciones.module"},"UbicacionesPageRoutingModule":{"hasNamespace":false,"type":0,"moduleName":"ubicaciones-routing.module","relativePath":"src\\app\\ubicaciones\\ubicaciones-routing.module"},"SucursalesPageModule":{"hasNamespace":false,"type":0,"moduleName":"sucursales.module","relativePath":"src\\app\\sucursales\\sucursales.module"},"SucursalesPageRoutingModule":{"hasNamespace":false,"type":0,"moduleName":"sucursales-routing.module","relativePath":"src\\app\\sucursales\\sucursales-routing.module"},"ProductoPageModule":{"hasNamespace":false,"type":0,"moduleName":"producto.module","relativePath":"src\\app\\producto\\producto.module"},"ProductoPageRoutingModule":{"hasNamespace":false,"type":0,"moduleName":"producto-routing.module","relativePath":"src\\app\\producto\\producto-routing.module"},"RegisterPageModule":{"hasNamespace":false,"type":0,"moduleName":"register.module","relativePath":"src\\app\\register\\register.module"},"RegisterPageRoutingModule":{"hasNamespace":false,"type":0,"moduleName":"register-routing.module","relativePath":"src\\app\\register\\register-routing.module"},"ProductoPage":{"hasNamespace":false,"type":0,"moduleName":"producto.page","relativePath":"src\\app\\producto\\producto.page"},"NotificacionesPage":{"hasNamespace":false,"type":0,"moduleName":"notificaciones.page","relativePath":"src\\app\\notificaciones\\notificaciones.page"},"PrincipalPage":{"hasNamespace":false,"type":0,"moduleName":"principal.page","relativePath":"src\\app\\principal\\principal.page"},"NotificacionesPageModule":{"hasNamespace":false,"type":0,"moduleName":"notificaciones.module","relativePath":"src\\app\\notificaciones\\notificaciones.module"},"NotificacionesPageRoutingModule":{"hasNamespace":false,"type":0,"moduleName":"notificaciones-routing.module","relativePath":"src\\app\\notificaciones\\notificaciones-routing.module"},"PrincipalPageModule":{"hasNamespace":false,"type":0,"moduleName":"principal.module","relativePath":"src\\app\\principal\\principal.module"},"PrincipalPageRoutingModule":{"hasNamespace":false,"type":0,"moduleName":"principal-routing.module","relativePath":"src\\app\\principal\\principal-routing.module"},"LoginPageModule":{"hasNamespace":false,"type":0,"moduleName":"login.module","relativePath":"src\\app\\login\\login.module"},"LoginPageRoutingModule":{"hasNamespace":false,"type":0,"moduleName":"login-routing.module","relativePath":"src\\app\\login\\login-routing.module"},"Task":{"hasNamespace":false,"type":1,"moduleName":"task","relativePath":"src\\app\\interfaces\\task"},"Sucursal":{"hasNamespace":false,"type":1,"moduleName":"task","relativePath":"src\\app\\interfaces\\task"},"LoginPage":{"hasNamespace":false,"type":0,"moduleName":"login.page","relativePath":"src\\app\\login\\login.page"},"HomePage":{"hasNamespace":false,"type":0,"moduleName":"home.page","relativePath":"src\\app\\home\\home.page"},"HomePageModule":{"hasNamespace":false,"type":0,"moduleName":"home.module","relativePath":"src\\app\\home\\home.module"},"HomePageRoutingModule":{"hasNamespace":false,"type":0,"moduleName":"home-routing.module","relativePath":"src\\app\\home\\home-routing.module"},"CheckoutPage":{"hasNamespace":false,"type":0,"moduleName":"checkout.page","relativePath":"src\\app\\checkout\\checkout.page"},"CheckoutPageModule":{"hasNamespace":false,"type":0,"moduleName":"checkout.module","relativePath":"src\\app\\checkout\\checkout.module"},"CheckoutPageRoutingModule":{"hasNamespace":false,"type":0,"moduleName":"checkout-routing.module","relativePath":"src\\app\\checkout\\checkout-routing.module"},"CategoriasPageModule":{"hasNamespace":false,"type":0,"moduleName":"categorias.module","relativePath":"src\\app\\categorias\\categorias.module"},"CategoriasPageRoutingModule":{"hasNamespace":false,"type":0,"moduleName":"categorias-routing.module","relativePath":"src\\app\\categorias\\categorias-routing.module"},"ForgotPasswordPage":{"hasNamespace":false,"type":0,"moduleName":"forgot-password.page","relativePath":"src\\app\\forgot-password\\forgot-password.page"},"ForgotPasswordPageModule":{"hasNamespace":false,"type":0,"moduleName":"forgot-password.module","relativePath":"src\\app\\forgot-password\\forgot-password.module"},"ForgotPasswordPageRoutingModule":{"hasNamespace":false,"type":0,"moduleName":"forgot-password-routing.module","relativePath":"src\\app\\forgot-password\\forgot-password-routing.module"},"CategoriasPage":{"hasNamespace":false,"type":0,"moduleName":"categorias.page","relativePath":"src\\app\\categorias\\categorias.page"},"CategoriaPage":{"hasNamespace":false,"type":0,"moduleName":"categoria.page","relativePath":"src\\app\\categoria\\categoria.page"},"CategoriaPageModule":{"hasNamespace":false,"type":0,"moduleName":"categoria.module","relativePath":"src\\app\\categoria\\categoria.module"},"CategoriaPageRoutingModule":{"hasNamespace":false,"type":0,"moduleName":"categoria-routing.module","relativePath":"src\\app\\categoria\\categoria-routing.module"},"CarritoPage":{"hasNamespace":false,"type":0,"moduleName":"carrito.page","relativePath":"src\\app\\carrito\\carrito.page"},"CarritoPageModule":{"hasNamespace":false,"type":0,"moduleName":"carrito.module","relativePath":"src\\app\\carrito\\carrito.module"},"AuthPageRoutingModule":{"hasNamespace":false,"type":0,"moduleName":"auth-routing.module","relativePath":"src\\app\\auth\\auth-routing.module"},"CarritoPageRoutingModule":{"hasNamespace":false,"type":0,"moduleName":"carrito-routing.module","relativePath":"src\\app\\carrito\\carrito-routing.module"},"AppRoutingModule":{"hasNamespace":false,"type":0,"moduleName":"app-routing.module","relativePath":"src\\app\\app-routing.module"},"AuthPage":{"hasNamespace":false,"type":0,"moduleName":"auth.page","relativePath":"src\\app\\auth\\auth.page"},"AuthPageModule":{"hasNamespace":false,"type":0,"moduleName":"auth.module","relativePath":"src\\app\\auth\\auth.module"},"Window":{"hasNamespace":false,"type":1,"moduleName":"index.d","relativePath":"plugins\\cordova-plugin-statusbar\\types\\index.d"},"StatusBar":{"hasNamespace":false,"type":1,"moduleName":"index.d","relativePath":"plugins\\cordova-plugin-statusbar\\types\\index.d"},"Navigator":{"hasNamespace":false,"type":1,"moduleName":"index.d","relativePath":"plugins\\cordova-plugin-splashscreen\\types\\index.d"},"Device":{"hasNamespace":false,"type":1,"moduleName":"index.d","relativePath":"plugins\\cordova-plugin-device\\types\\index.d"},"AppPage":{"hasNamespace":false,"type":0,"moduleName":"app.po","relativePath":"e2e\\src\\app.po"},"TaskService":{"hasNamespace":false,"type":0,"moduleName":"task.service","relativePath":"src\\app\\services\\task.service"},"RegisterPage":{"hasNamespace":false,"type":0,"moduleName":"register.page","relativePath":"src\\app\\register\\register.page"},"UbicacionesPage":{"hasNamespace":false,"type":0,"moduleName":"ubicaciones.page","relativePath":"src\\app\\ubicaciones\\ubicaciones.page"},"MarcadoMap":{"hasNamespace":false,"type":1,"moduleName":"sucursales.page","relativePath":"src\\app\\sucursales\\sucursales.page"},"informacionSucursal":{"hasNamespace":false,"type":1,"moduleName":"sucursales.page","relativePath":"src\\app\\sucursales\\sucursales.page"},"SucursalesPage":{"hasNamespace":false,"type":0,"moduleName":"sucursales.page","relativePath":"src\\app\\sucursales\\sucursales.page"}},"files":{"src\\zone-flags.ts":"2020-12-17T00:56:27.968Z","src\\test.ts":"2020-12-17T00:56:27.967Z","src\\polyfills.ts":"2020-12-17T00:56:27.967Z","src\\main.ts":"2020-12-17T00:56:27.967Z","src\\environments\\environment.ts":"2020-12-17T00:56:27.966Z","src\\environments\\environment.prod.ts":"2020-12-17T00:56:27.966Z","src\\declarations.d.ts":"2020-12-17T00:56:27.965Z","src\\app\\app.component.ts":"2020-12-17T00:56:27.894Z","src\\app\\app.module.ts":"2020-12-17T00:56:27.894Z","src\\app\\app.component.spec.ts":"2020-12-17T00:56:27.893Z","src\\app\\ubicaciones\\ubicaciones.page.ts":"2020-12-17T03:28:37.739Z","src\\app\\ubicaciones\\ubicaciones.page.spec.ts":"2020-12-17T00:56:27.934Z","src\\app\\ubicaciones\\ubicaciones.module.ts":"2020-12-17T00:56:27.933Z","src\\app\\ubicaciones\\ubicaciones-routing.module.ts":"2020-12-17T00:56:27.933Z","src\\app\\sucursales\\sucursales.page.ts":"2020-12-19T21:26:19.659Z","src\\app\\sucursales\\sucursales.page.spec.ts":"2020-12-17T00:56:27.932Z","src\\app\\sucursales\\sucursales.module.ts":"2020-12-17T00:56:27.931Z","src\\app\\sucursales\\sucursales-routing.module.ts":"2020-12-17T00:56:27.931Z","src\\app\\services\\task.service.ts":"2020-12-17T03:25:10.828Z","src\\app\\services\\task.service.spec.ts":"2020-12-17T00:56:27.930Z","src\\app\\producto\\producto.module.ts":"2020-12-17T00:56:27.926Z","src\\app\\producto\\producto-routing.module.ts":"2020-12-17T00:56:27.926Z","src\\app\\register\\register.page.ts":"2020-12-17T03:25:31.657Z","src\\app\\register\\register.page.spec.ts":"2020-12-17T00:56:27.929Z","src\\app\\register\\register.module.ts":"2020-12-17T00:56:27.928Z","src\\app\\register\\register-routing.module.ts":"2020-12-17T00:56:27.928Z","src\\app\\producto\\producto.page.ts":"2020-12-17T00:56:27.928Z","src\\app\\producto\\producto.page.spec.ts":"2020-12-17T00:56:27.927Z","src\\app\\notificaciones\\notificaciones.page.ts":"2020-12-17T00:56:27.923Z","src\\app\\notificaciones\\notificaciones.page.spec.ts":"2020-12-17T00:56:27.923Z","src\\app\\principal\\principal.page.ts":"2020-12-17T00:56:27.926Z","src\\app\\principal\\principal.page.spec.ts":"2020-12-17T00:56:27.925Z","src\\app\\notificaciones\\notificaciones.module.ts":"2020-12-17T00:56:27.921Z","src\\app\\notificaciones\\notificaciones-routing.module.ts":"2020-12-17T00:56:27.921Z","src\\app\\principal\\principal.module.ts":"2020-12-17T00:56:27.924Z","src\\app\\principal\\principal-routing.module.ts":"2020-12-17T00:56:27.923Z","src\\app\\login\\login.module.ts":"2020-12-17T00:56:27.917Z","src\\app\\login\\login-routing.module.ts":"2020-12-17T00:56:27.917Z","src\\app\\interfaces\\task.ts":"2020-12-17T00:56:27.917Z","src\\app\\login\\login.page.ts":"2020-12-17T00:56:27.921Z","src\\app\\login\\login.page.spec.ts":"2020-12-17T00:56:27.920Z","src\\app\\home\\home.page.ts":"2020-12-17T00:56:27.915Z","src\\app\\home\\home.page.spec.ts":"2020-12-17T00:56:27.914Z","src\\app\\home\\home.module.ts":"2020-12-17T00:56:27.912Z","src\\app\\home\\home-routing.module.ts":"2020-12-17T00:56:27.912Z","src\\app\\checkout\\checkout.page.ts":"2020-12-17T00:56:27.909Z","src\\app\\checkout\\checkout.page.spec.ts":"2020-12-17T00:56:27.908Z","src\\app\\checkout\\checkout.module.ts":"2020-12-17T00:56:27.907Z","src\\app\\checkout\\checkout-routing.module.ts":"2020-12-17T00:56:27.906Z","src\\app\\categorias\\categorias.module.ts":"2020-12-17T00:56:27.903Z","src\\app\\categorias\\categorias-routing.module.ts":"2020-12-17T00:56:27.903Z","src\\app\\forgot-password\\forgot-password.page.ts":"2020-12-17T00:56:27.912Z","src\\app\\forgot-password\\forgot-password.page.spec.ts":"2020-12-17T00:56:27.911Z","src\\app\\forgot-password\\forgot-password.module.ts":"2020-12-17T00:56:27.910Z","src\\app\\forgot-password\\forgot-password-routing.module.ts":"2020-12-17T00:56:27.910Z","src\\app\\categorias\\categorias.page.ts":"2020-12-17T00:56:27.905Z","src\\app\\categorias\\categorias.page.spec.ts":"2020-12-17T00:56:27.904Z","src\\app\\categoria\\categoria.page.ts":"2020-12-17T00:56:27.902Z","src\\app\\categoria\\categoria.page.spec.ts":"2020-12-17T00:56:27.901Z","src\\app\\categoria\\categoria.module.ts":"2020-12-17T00:56:27.900Z","src\\app\\categoria\\categoria-routing.module.ts":"2020-12-17T00:56:27.900Z","src\\app\\carrito\\carrito.page.ts":"2020-12-17T00:56:27.899Z","src\\app\\carrito\\carrito.page.spec.ts":"2020-12-17T00:56:27.898Z","src\\app\\carrito\\carrito.module.ts":"2020-12-17T00:56:27.897Z","src\\app\\auth\\auth-routing.module.ts":"2020-12-17T00:56:27.895Z","src\\app\\carrito\\carrito-routing.module.ts":"2020-12-17T00:56:27.897Z","src\\app\\app-routing.module.ts":"2020-12-17T00:56:27.892Z","src\\app\\auth\\auth.page.ts":"2020-12-17T00:56:27.897Z","src\\app\\auth\\auth.page.spec.ts":"2020-12-17T00:56:27.896Z","src\\app\\auth\\auth.module.ts":"2020-12-17T00:56:27.895Z","plugins\\cordova-plugin-statusbar\\types\\index.d.ts":"2020-12-17T00:56:27.834Z","plugins\\cordova-plugin-splashscreen\\types\\index.d.ts":"2020-12-17T00:56:27.817Z","plugins\\cordova-plugin-device\\types\\index.d.ts":"2020-12-17T00:56:27.738Z","e2e\\src\\app.po.ts":"2020-12-17T00:55:22.897Z","e2e\\src\\app.e2e-spec.ts":"2020-12-17T00:55:22.896Z"}}